toopazo_ulg/__init__.py
toopazo_ulg/parse_file.py
toopazo_ulg/plot_basics.py
toopazo_ulg/plot_main.py
toopazo_ulg/plot_mixer.py
toopazo_ulg/plot_sysid.py
toopazo_ulg/px4_csv.py
toopazo_ulg-0.0.24.dist-info/LICENSE
toopazo_ulg-0.0.24.dist-info/METADATA
toopazo_ulg-0.0.24.dist-info/WHEEL
toopazo_ulg-0.0.24.dist-info/top_level.txt
toopazo_ulg-0.0.24.dist-info/RECORD
