Metadata-Version: 2.1
Name: toopazo-ulg
Version: 0.0.24
Summary: Python package to process and plot Px4 .ulg files
Home-page: https://github.com/toopazo/toopazo_ulg
Author: toopazo
Author-email: toopazo@protonmail.com
License: UNKNOWN
Platform: UNKNOWN
Classifier: Programming Language :: Python :: 3
Classifier: License :: OSI Approved :: MIT License
Classifier: Operating System :: OS Independent
Requires-Python: >=3.6
License-File: LICENSE
